{
  "$schema": "./node_modules/@biomejs/biome/configuration_schema.json",
  "vcs": {
    "enabled": false,
    "clientKind": "git",
    "useIgnoreFile": false
  },
  "files": {
    "ignoreUnknown": false
  },
  "formatter": {
    "enabled": true,
    "formatWithErrors": true,
    "indentStyle": "space",
    "lineWidth": 100
  },
  "organizeImports": {
    "enabled": true
  },
  "linter": {
    "enabled": true,
    "rules": {
      "recommended": true,
      "correctness": {
        "noUndeclaredVariables": "error",
        "useHookAtTopLevel": "error",
        "noUnusedVariables": "warn",
        "noUnusedImports": "warn",
        "noUnusedFunctionParameters": "warn"
      },
      "style": {
        "useConsistentArrayType": "warn",
        "useDefaultSwitchClause": "error",
        "useForOf": "warn",
        "useFragmentSyntax": "warn",
        "useThrowNewError": "error"
      },
      "suspicious": {
        "noEvolvingTypes": "error",
        "useAwait": "error",
        "noEmptyBlockStatements": "warn"
      }
    }
  },
  "javascript": {
    "formatter": {
      "indentStyle": "space",
      "lineWidth": 80,
      "quoteStyle": "double"
    }
  },
  "json": {
    "parser": {
      "allowTrailingCommas": true
    },
    "formatter": {
      "indentStyle": "space",
      "lineWidth": 80
    },
    "linter": {
      "enabled": true
    }
  }
}
